CTH_sentence_split/__init__.py
CTH_sentence_split/__main__.py
CTH_sentence_split/pkg/__init__.py
CTH_sentence_split/pkg/split.py
CTH_sentence_split/pkg/update_dict.py
CTH_sentence_split-0.0.24.dist-info/LICENSE
CTH_sentence_split-0.0.24.dist-info/METADATA
CTH_sentence_split-0.0.24.dist-info/WHEEL
CTH_sentence_split-0.0.24.dist-info/top_level.txt
CTH_sentence_split-0.0.24.dist-info/RECORD
