Metadata-Version: 2.1
Name: CTH-sentence-split
Version: 0.0.24
Summary: Chinese (Traditional), Taiwanese and Hakka's sentence split tool.
Home-page: https://github.com/eran0926/CTH_sentence_split
Author: Eran Hsu
Author-email: eran0926@gmail.com
License: UNKNOWN
Platform: UNKNOWN
Classifier: Programming Language :: Python :: 3
Classifier: License :: OSI Approved :: GNU Affero General Public License v3
Classifier: Operating System :: OS Independent
Classifier: Natural Language :: Chinese (Traditional)
Classifier: Development Status :: 4 - Beta
Requires-Python: >=3.5
